quickgrove-0.1.4.dist-info/METADATA
quickgrove-0.1.4.dist-info/WHEEL
quickgrove-0.1.4.dist-info/entry_points.txt
quickgrove-0.1.4.dist-info/licenses/LICENSE
quickgrove/__init__.py
quickgrove/generate_examples.py
quickgrove/_internal.cpython-312-aarch64-linux-gnu.so
quickgrove-0.1.4.dist-info/RECORD
