Metadata-Version: 2.4
Name: quickgrove
Version: 0.1.4
Requires-Dist: ibis-framework[datafusion,duckdb]>=9.5.0 ; extra == 'examples'
Requires-Dist: pandas>=2.2.3 ; extra == 'examples'
Requires-Dist: pyarrow>=17.0.0 ; extra == 'examples'
Requires-Dist: pythran>=0.17.0 ; extra == 'examples'
Requires-Dist: requests>=2.32.3 ; extra == 'examples'
Requires-Dist: scikit-learn>=1.6.0 ; extra == 'examples'
Requires-Dist: xgboost>=2.1.3 ; extra == 'examples'
Requires-Dist: pyarrow>=17.0.0 ; extra == 'pyarrow'
Provides-Extra: examples
Provides-Extra: pyarrow
License-File: LICENSE
Summary: 
Author-email: Hussain Sultan <hussain@letsql.com>
Requires-Python: >=3.10
